{
  "task_id": "MTASK-0085",
  "created_by": "windows-main",
  "worker_name": "ubuntu-atlas-01",
  "assigned_to": "ubuntu-worker-01",
  "required_worker_id": "ubuntu-worker-01",
  "executor_script": "pilot_v1/scripts/exec_mtask_0077_restart_customide_backend.sh",
  "objective": "Urgent hard reboot of CustomIDE backend/frontend stack: kill stale :5555/:5570 processes, restart clean, verify backend health and status bundle.",
  "moss_labels": [
    "moss/customide/phase35",
    "moss/worker",
    "moss/operations"
  ],
  "priority": "high",
  "risk_level": "low",
  "status": "approved_to_execute",
  "required_validation": [
    "stdout_excerpt includes backend_health=passed",
    "stdout_excerpt includes bundle_health=passed",
    "stdout_excerpt includes backend_restart=passed"
  ],
  "timeout_seconds": 900,
  "created_at_utc": "2026-04-23T00:00:00Z"
}
